optuna_dashboard/__init__.py
optuna_dashboard/_app.py
optuna_dashboard/_bottle_util.py
optuna_dashboard/_cli.py
optuna_dashboard/_custom_plot_data.py
optuna_dashboard/_form_widget.py
optuna_dashboard/_importance.py
optuna_dashboard/_inmemory_cache.py
optuna_dashboard/_named_objectives.py
optuna_dashboard/_note.py
optuna_dashboard/_pareto_front.py
optuna_dashboard/_preference_setting.py
optuna_dashboard/_preferential_history.py
optuna_dashboard/_rdb_migration.py
optuna_dashboard/_serializer.py
optuna_dashboard/_sql_profiler.py
optuna_dashboard/_storage.py
optuna_dashboard/_storage_url.py
optuna_dashboard/app.py
optuna_dashboard/index.html
optuna_dashboard/artifact/__init__.py
optuna_dashboard/artifact/_backend.py
optuna_dashboard/artifact/_backend_to_store.py
optuna_dashboard/artifact/backoff.py
optuna_dashboard/artifact/boto3.py
optuna_dashboard/artifact/exceptions.py
optuna_dashboard/artifact/file_system.py
optuna_dashboard/artifact/prefix.py
optuna_dashboard/artifact/protocol.py
optuna_dashboard/img/favicon.ico
optuna_dashboard/img/favicon.ico.gz
optuna_dashboard/preferential/__init__.py
optuna_dashboard/preferential/_study.py
optuna_dashboard/preferential/_system_attrs.py
optuna_dashboard/preferential/samplers/__init__.py
optuna_dashboard/preferential/samplers/gp.py
optuna_dashboard/public/bundle.js
optuna_dashboard/public/bundle.js.LICENSE.txt
optuna_dashboard/public/bundle.js.LICENSE.txt.gz
optuna_dashboard/public/bundle.js.gz
optuna_dashboard/streamlit/__init__.py
optuna_dashboard/streamlit/_streamlit_helper.py
optuna_dashboard-0.19.0.dist-info/licenses/LICENSE
optuna_dashboard-0.19.0.dist-info/METADATA
optuna_dashboard-0.19.0.dist-info/WHEEL
optuna_dashboard-0.19.0.dist-info/entry_points.txt
optuna_dashboard-0.19.0.dist-info/top_level.txt
optuna_dashboard-0.19.0.dist-info/RECORD
