Metadata-Version: 2.4
Name: optuna-dashboard
Version: 0.19.0
Summary: Real-time dashboard for Optuna
Author-email: Masashi Shibata <mshibata@preferred.jp>
License: MIT License
Project-URL: Homepage, https://github.com/optuna/optuna-dashboard
Project-URL: Sources, https://github.com/optuna/optuna-dashboard
Project-URL: Bug Tracker, https://github.com/optuna/optuna-dashboard/issues
Classifier: Development Status :: 3 - Alpha
Classifier: Intended Audience :: Developers
Classifier: License :: OSI Approved :: MIT License
Classifier: Programming Language :: Python
Classifier: Programming Language :: Python :: 3
Classifier: Programming Language :: Python :: 3.8
Classifier: Programming Language :: Python :: 3.9
Classifier: Programming Language :: Python :: 3.10
Classifier: Programming Language :: Python :: 3.11
Classifier: Programming Language :: Python :: 3.12
Classifier: Programming Language :: Python :: 3.13
Classifier: Programming Language :: Python :: 3 :: Only
Classifier: Intended Audience :: Science/Research
Requires-Python: >=3.8
License-File: LICENSE
Requires-Dist: bottle>=0.13.0
Requires-Dist: optuna>=3.1.0
Requires-Dist: packaging
Requires-Dist: scikit-learn
Provides-Extra: docs
Requires-Dist: boto3; extra == "docs"
Requires-Dist: botorch; extra == "docs"
Requires-Dist: streamlit; extra == "docs"
Requires-Dist: sphinx; extra == "docs"
Requires-Dist: sphinx_rtd_theme; extra == "docs"
Provides-Extra: test
Requires-Dist: coverage; extra == "test"
Requires-Dist: plotly; extra == "test"
Requires-Dist: pytest; extra == "test"
Requires-Dist: moto[s3]; extra == "test"
Provides-Extra: optional
Requires-Dist: streamlit; extra == "optional"
Requires-Dist: boto3; extra == "optional"
Requires-Dist: botorch>=0.8.1; python_version >= "3.8" and extra == "optional"
Provides-Extra: preferential
Requires-Dist: botorch>=0.8.1; extra == "preferential"
Provides-Extra: plotlypy
Requires-Dist: plotly; extra == "plotlypy"
Dynamic: license-file
